README.md
setup.py
pyper/__init__.py
pyper/client.py
pyper/common.py
pyper/server.py
pyper_piper.egg-info/PKG-INFO
pyper_piper.egg-info/SOURCES.txt
pyper_piper.egg-info/dependency_links.txt
pyper_piper.egg-info/top_level.txt