Metadata-Version: 2.1
Name: pyper-piper
Version: 0.1.5
Summary: The Piper networking protocol in Python.
Home-page: https://github.com/Bigjango13/Pyper
Author: Bigjango13
License: MIT
Platform: UNKNOWN
Classifier: Development Status :: 3 - Alpha
Classifier: Environment :: Web Environment
Classifier: Operating System :: OS Independent
Classifier: Programming Language :: Python :: 3
Classifier: Topic :: Communications
Classifier: Topic :: Communications :: File Sharing
Classifier: Topic :: Internet
Classifier: Topic :: System :: Networking
